task3/dual_ram.sv
module dual_ram #(
    parameter ADDRESS_WIDTH = 8,
              DATA_WIDTH = 8
)(
    input logic clk,
    input logic wr_en,
    input logic rd_en,
    input logic [ADDRESS_WIDTH-1:0] wr_addr,
    input logic [ADDRESS_WIDTH-1:0] rd_addr,
    input logic [DATA_WIDTH-1:0] din,
    output logic [DATA_WIDTH-1:0] dout
);

logic [DATA_WIDTH-1:0] ram_array [2**ADDRESS_WIDTH-1:0];

always_ff @(posedge clk) begin
    if (wr_en == 1'b1) ram_array[wr_addr] <= din;
    if (rd_en == 1'b1) dout <= ram_array [rd_addr];
end 

endmodule

task3/counter.sv
module counter #(
    parameter WIDTH = 8
)(
    input logic clk,
    input logic rst,
    input logic en,
    input logic [WIDTH-1:0] offset,
    output logic [WIDTH-1:0] count1,
    output logic [WIDTH-1:0] count2
);

always_ff @ (posedge clk) begin
    if (rst) begin
        count1 <= {WIDTH{1'b0}};
        count2 <= {WIDTH{1'b0}} + offset;                
    end else begin
        count1 <= count1 + {{WIDTH-1{1'b0}}, en};
        count2 <= count1 + {{WIDTH-1{1'b0}}, en} + offset;
    end
end

endmodule

task3/sigdelay.sv
module sigdelay #(
  parameter WIDTH = 8
)(
  input logic clk,
  input logic rst,
  input logic wr,
  input logic rd,
  input logic offset,
  input logic mic_signal,
  output logic [WIDTH-1:0] delayed_signal
);

  logic [WIDTH-1:0] count1;
  logic [WIDTH-1:0] count2;

counter myCounter (
  .clk (clk),
  .rst (rst),
  .en (1),
  .offset (offset),
  .count1 (count1),
  .count2 (count2)
);

dual_ram myDualRam (
  .clk (clk),
  .wr_en (wr),
  .rd_en (rd),
  .wr_addr (count2),
  .rd_addr (count1),
  .din (mic_signal),
  .dout (delayed_signal)
);

endmodule

task3/sigdelay.vcd
$version Generated by VerilatedVcd $end
$date Tue Nov  5 14:47:16 2024 $end
$timescale 1ps $end

 $scope module TOP $end
  $var wire  1 # clk $end
  $var wire  8 ) delayed_signal [7:0] $end
  $var wire  1 ( mic_signal $end
  $var wire  1 ' offset $end
  $var wire  1 & rd $end
  $var wire  1 $ rst $end
  $var wire  1 % wr $end
  $scope module sigdelay $end
   $var wire 32 . WIDTH [31:0] $end
   $var wire  1 # clk $end
   $var wire  8 * count1 [7:0] $end
   $var wire  8 + count2 [7:0] $end
   $var wire  8 ) delayed_signal [7:0] $end
   $var wire  1 ( mic_signal $end
   $var wire  1 ' offset $end
   $var wire  1 & rd $end
   $var wire  1 $ rst $end
   $var wire  1 % wr $end
   $scope module myCounter $end
    $var wire 32 . WIDTH [31:0] $end
    $var wire  1 # clk $end
    $var wire  8 * count1 [7:0] $end
    $var wire  8 + count2 [7:0] $end
    $var wire  1 / en $end
    $var wire  8 , offset [7:0] $end
    $var wire  1 $ rst $end
   $upscope $end
   $scope module myDualRam $end
    $var wire 32 . ADDRESS_WIDTH [31:0] $end
    $var wire 32 . DATA_WIDTH [31:0] $end
    $var wire  1 # clk $end
    $var wire  8 - din [7:0] $end
    $var wire  8 ) dout [7:0] $end
    $var wire  8 * rd_addr [7:0] $end
    $var wire  1 & rd_en $end
    $var wire  8 + wr_addr [7:0] $end
    $var wire  1 % wr_en $end
   $upscope $end
  $upscope $end
 $upscope $end
$enddefinitions $end


#0
1#
0$
1%
1&
p'
0(
b00000000 )
b00000000 *
b00000000 +
b01000000 ,
b00000000 -
b00000000000000000000000000001000 .
1/
#1
0#
#2
1#
3'
·(
b00000001 *
b01000001 +
b00110011 ,
b10000111 -
#3
0#
#4
1#
»(
b00000010 *
b00110101 +
b10001011 -
#5
0#
#6
1#
¹(
b00000011 *
b00110110 +
b10001001 -
#7
0#
#8
1#
±(
b00000100 *
b00110111 +
b10010001 -
#9
0#
#10
1#
½(
b00000101 *
b00111000 +
b10001101 -
#11
0#
#12
1#
¹(
b00000110 *
b00111001 +
b10011001 -
#13
0#
#14
1#
¾(
b00000111 *
b00111010 +
b10001110 -
#15
0#
#16
1#
r(
b00001000 *
b00111011 +
b01110010 -
#17
0#
#18
1#
t(
b00001001 *
b00111100 +
b01110100 -
#19
0#
#20
1#
q(
b00001010 *
b00111101 +
b01110001 -
#21
0#
#22
1#
w(
b00001011 *
b00111110 +
b01010111 -
#23
0#
#24
1#
y(
b00001100 *
b00111111 +
b01011001 -
#25
0#
#26
1#
r(
b00001101 *
b01000000 +
b01100010 -
#27
0#
#28
1#
p(
b00001110 *
b01000001 +
b01010000 -
#29
0#
#30
1#
b00001111 *
b01000010 +
#31
0#
#32
1#
v(
b00010000 *
b01000011 +
b01100110 -
#33
0#
#34
1#
w(
b00010001 *
b01000100 +
b01010111 -
#35
0#
#36
1#
(
b00010010 *
b01000101 +
b01011111 -
#37
0#
#38
1#
x(
b00010011 *
b01000110 +
b01111000 -
#39
0#
#40
1#
v(
b00010100 *
b01000111 +
b01110110 -
#41
0#
#42
1#
r(
b00010101 *
b01001000 +
b01110010 -
#43
0#
#44
1#
|(
b00010110 *
b01001001 +
b01111100 -
#45
0#
#46
1#
s(
b00010111 *
b01001010 +
b01110011 -
#47
0#
#48
1#
|(
b00011000 *
b01001011 +
b01101100 -
#49
0#
#50
1#
u(
b00011001 *
b01001100 +
b01110101 -
#51
0#
#52
1#
{(
b00011010 *
b01001101 +
b01101011 -
#53
0#
#54
1#
(
b00011011 *
b01001110 +
b01011111 -
#55
0#
#56
1#
q(
b00011100 *
b01001111 +
b01100001 -
#57
0#
#58
1#
~(
b00011101 *
b01010000 +
b01011110 -
#59
0#
#60
1#
x(
b00011110 *
b01010001 +
b01011000 -
#61
0#
#62
1#
q(
b00011111 *
b01010010 +
b01100001 -
#63
0#
#64
1#
t(
b00100000 *
b01010011 +
b01100100 -
#65
0#
#66
1#
{(
b00100001 *
b01010100 +
b01101011 -
#67
0#
#68
1#
|(
b00100010 *
b01010101 +
b01111100 -
#69
0#
#70
1#
r(
b00100011 *
b01010110 +
b01110010 -
#71
0#
#72
1#
q(
b00100100 *
b01010111 +
b01110001 -
#73
0#
#74
1#
u(
b00100101 *
b01011000 +
b01110101 -
#75
0#
#76
1#
p(
b00100110 *
b01011001 +
b01110000 -
#77
0#
#78
1#
r(
b00100111 *
b01011010 +
b01100010 -
#79
0#
#80
1#
v(
b00101000 *
b01011011 +
b01100110 -
#81
0#
#82
1#
(
b00101001 *
b01011100 +
b01011111 -
#83
0#
#84
1#
w(
b00101010 *
b01011101 +
b01000111 -
#85
0#
#86
1#
v(
b00101011 *
b01011110 +
b01000110 -
#87
0#
#88
1#
~(
b00101100 *
b01011111 +
b01001110 -
#89
0#
#90
1#
}(
b00101101 *
b01100000 +
b01001101 -
#91
0#
#92
1#
r(
b00101110 *
b01100001 +
b01010010 -
#93
0#
#94
1#
(
b00101111 *
b01100010 +
b01001111 -
#95
0#
#96
1#
(
b00110000 *
b01100011 +
b01011111 -
#97
0#
#98
1#
s(
b00110001 *
b01100100 +
b01110011 -
#99
0#
#100
1#
v(
b00110010 *
b01100101 +
b01110110 -
#101
0#
#102
1#
{(
b00110011 *
b01100110 +
b01111011 -
#103
0#
#104
1#
´(
b00110100 *
b01100111 +
b10000100 -
#105
0#
#106
1#
¼(
b00110101 *
b01101000 +
b10001100 -
#107
0#
#108
1#
´(
b10001011 )
b00110110 *
b01101001 +
b10010100 -
#109
0#
#110
1#
±(
b10001001 )
b00110111 *
b01101010 +
b10010001 -
#111
0#
#112
1#
²(
b10010001 )
b00111000 *
b01101011 +
b10000010 -
#113
0#
#114
1#
·(
b10001101 )
b00111001 *
b01101100 +
b10000111 -
#115
0#
#116
1#
±(
b10011001 )
b00111010 *
b01101101 +
b10000001 -
#117
0#
#118
1#
t(
b10001110 )
b00111011 *
b01101110 +
b01110100 -
#119
0#
#120
1#
z(
b01110010 )
b00111100 *
b01101111 +
b01111010 -
#121
0#
#122
1#
~(
b01110100 )
b00111101 *
b01110000 +
b01111110 -
#123
0#
#124
1#
{(
b01110001 )
b00111110 *
b01110001 +
b01111011 -
#125
0#
#126
1#
x(
b01010111 )
b00111111 *
b01110010 +
b01111000 -
#127
0#
#128
1#
}(
b01011001 )
b01000000 *
b01110011 +
b01111101 -
#129
0#
#130
1#
·(
b01100010 )
b01000001 *
b01110100 +
b10000111 -
#131
0#
#132
1#
°(
b01010000 )
b01000010 *
b01110101 +
b10000000 -
#133
0#
#134
1#
r(
b01000011 *
b01110110 +
b01110010 -
#135
0#
#136
1#
{(
b01100110 )
b01000100 *
b01110111 +
b01101011 -
#137
0#
#138
1#
|(
b01010111 )
b01000101 *
b01111000 +
b01111100 -
#139
0#
#140
1#
u(
b01011111 )
b01000110 *
b01111001 +
b01110101 -
#141
0#
#142
1#
t(
b01111000 )
b01000111 *
b01111010 +
b01100100 -
#143
0#
#144
1#
~(
b01110110 )
b01001000 *
b01111011 +
b01011110 -
#145
0#
#146
1#
w(
b01110010 )
b01001001 *
b01111100 +
b01010111 -
#147
0#
#148
1#
|(
b01111100 )
b01001010 *
b01111101 +
b01001100 -
#149
0#
#150
1#
~(
b01110011 )
b01001011 *
b01111110 +
b01001110 -
#151
0#
#152
1#
x(
b01101100 )
b01001100 *
b01111111 +
b01011000 -
#153
0#
#154
1#
t(
b01110101 )
b01001101 *
b10000000 +
b01010100 -
#155
0#
#156
1#
p(
b01101011 )
b01001110 *
b10000001 +
b01010000 -
#157
0#
#158
1#
w(
b01011111 )
b01001111 *
b10000010 +
b01010111 -
#159
0#
#160
1#
s(
b01100001 )
b01010000 *
b10000011 +
b01100011 -
#161
0#
#162
1#
x(
b01011110 )
b01010001 *
b10000100 +
b01101000 -
#163
0#
#164
1#
~(
b01011000 )
b01010010 *
b10000101 +
b01101110 -
#165
0#
#166
1#
{(
b01100001 )
b01010011 *
b10000110 +
b01101011 -
#167
0#
#168
1#
t(
b01100100 )
b01010100 *
b10000111 +
b01110100 -
#169
0#
#170
1#
¶(
b01101011 )
b01010101 *
b10001000 +
b10000110 -
#171
0#
#172
1#
}(
b01111100 )
b01010110 *
b10001001 +
b01101101 -
#173
0#
#174
1#
v(
b01110010 )
b01010111 *
b10001010 +
b01100110 -
#175
0#
#176
1#
s(
b01110001 )
b01011000 *
b10001011 +
b01100011 -
#177
0#
#178
1#
q(
b01110101 )
b01011001 *
b10001100 +
b01110001 -
#179
0#
#180
1#
|(
b01110000 )
b01011010 *
b10001101 +
b01101100 -
#181
0#
#182
1#
r(
b01100010 )
b01011011 *
b10001110 +
b01100010 -
#183
0#
#184
1#
(
b01100110 )
b01011100 *
b10001111 +
b01011111 -
#185
0#
#186
1#
r(
b01011111 )
b01011101 *
b10010000 +
b01100010 -
#187
0#
#188
1#
y(
b01000111 )
b01011110 *
b10010001 +
b01111001 -
#189
0#
#190
1#
p(
b01000110 )
b01011111 *
b10010010 +
b01110000 -
#191
0#
#192
1#
|(
b01001110 )
b01100000 *
b10010011 +
b01101100 -
#193
0#
#194
1#
¶(
b01001101 )
b01100001 *
b10010100 +
b10000110 -
#195
0#
#196
1#
±(
b01010010 )
b01100010 *
b10010101 +
b10000001 -
#197
0#
#198
1#
}(
b01001111 )
b01100011 *
b10010110 +
b01101101 -
#199
0#
#200
1#
|(
b01011111 )
b01100100 *
b10010111 +
b01111100 -
#201
0#
#202
1#
(
b01110011 )
b01100101 *
b10011000 +
b01101111 -
#203
0#
#204
1#
s(
b01110110 )
b01100110 *
b10011001 +
b01100011 -
#205
0#
#206
1#
}(
b01111011 )
b01100111 *
b10011010 +
b01101101 -
#207
0#
#208
1#
y(
b10000100 )
b01101000 *
b10011011 +
b01101001 -
#209
0#
#210
1#
z(
b10001100 )
b01101001 *
b10011100 +
b01011010 -
#211
0#
#212
1#
}(
b10010100 )
b01101010 *
b10011101 +
b01001101 -
#213
0#
#214
1#
q(
b10010001 )
b01101011 *
b10011110 +
b01010001 -
#215
0#
#216
1#
}(
b10000010 )
b01101100 *
b10011111 +
b01011101 -
#217
0#
#218
1#
s(
b10000111 )
b01101101 *
b10100000 +
b01100011 -
#219
0#
#220
1#
(
b10000001 )
b01101110 *
b10100001 +
b01011111 -
#221
0#
#222
1#
x(
b01110100 )
b01101111 *
b10100010 +
b01101000 -
#223
0#
#224
1#
q(
b01111010 )
b01110000 *
b10100011 +
b01110001 -
#225
0#
#226
1#
s(
b01111110 )
b01110001 *
b10100100 +
b01110011 -
#227
0#
#228
1#
2'
b01111011 )
b01110010 *
b10100101 +
b00110010 ,
#229
0#
#230
1#
1'
|(
b01111000 )
b01110011 *
b00110001 ,
b01111100 -
#231
0#
#232
1#
0'
p(
b01111101 )
b01110100 *
b00110000 ,
b01110000 -
#233
0#
#234
1#
?'
s(
b10000111 )
b01110101 *
b00101111 ,
b01100011 -
#235
0#
#236
1#
='
|(
b10000000 )
b01110110 *
b00101101 ,
b01011100 -
#237
0#
#238
1#
q(
b01110010 )
b01110111 *
b10100100 +
b01010001 -
#239
0#
#240
1#
<'
v(
b01101011 )
b01111000 *
b10100101 +
b00101100 ,
b01010110 -
#241
0#
#242
1#
~(
b01111100 )
b01111001 *
b01001110 -
#243
0#
#244
1#
r(
b01110101 )
b01111010 *
b10100110 +
b01010010 -
#245
0#
#246
1#
(
b01100100 )
b01111011 *
b10100111 +
b01011111 -
#247
0#
#248
1#
u(
b01011110 )
b01111100 *
b10101000 +
b01100101 -
#249
0#
#250
1#
x(
b01010111 )
b01111101 *
b10101001 +
b01101000 -
#251
0#
#252
1#
(
b01001100 )
b01111110 *
b10101010 +
b01111111 -
#253
0#
#254
1#
°(
b01001110 )
b01111111 *
b10101011 +
b10010000 -
#255
0#
#256
1#
»(
b01011000 )
b10000000 *
b10101100 +
b10001011 -
#257
0#
#258
1#
;'
±(
b01010100 )
b10000001 *
b10101101 +
b00101011 ,
b10010001 -
#259
0#
#260
1#
9'
»(
b01010000 )
b10000010 *
b00101001 ,
b10001011 -
#261
0#
#262
1#
8'
¶(
b01010111 )
b10000011 *
b10101100 +
b00101000 ,
b10000110 -
#263
0#
#264
1#
6'
y(
b01100011 )
b10000100 *
b00100110 ,
b01111001 -
#265
0#
#266
1#
5'
|(
b01101000 )
b10000101 *
b10101011 +
b00100101 ,
b01101100 -
#267
0#
#268
1#
4'
s(
b01101110 )
b10000110 *
b00100100 ,
b01100011 -
#269
0#
#270
1#
r(
b01101011 )
b10000111 *
b01100010 -
#271
0#
#272
1#
u(
b01110100 )
b10001000 *
b10101100 +
b01010101 -
#273
0#
#274
1#
y(
b10000110 )
b10001001 *
b10101101 +
b01001001 -
#275
0#
#276
1#
s(
b01101101 )
b10001010 *
b10101110 +
b01010011 -
#277
0#
#278
1#
y(
b01100110 )
b10001011 *
b10101111 +
b01011001 -
#279
0#
#280
1#
z(
b01100011 )
b10001100 *
b10110000 +
b01101010 -
#281
0#
#282
1#
2'
(
b01110001 )
b10001101 *
b10110001 +
b00100010 ,
b01101111 -
#283
0#
#284
1#
?'
w(
b01101100 )
b10001110 *
b10110000 +
b00011111 ,
b01100111 -
#285
0#
#286
1#
>'
r(
b01100010 )
b10001111 *
b10101110 +
b00011110 ,
b01110010 -
#287
0#
#288
1#
='
·(
b01011111 )
b10010000 *
b00011101 ,
b10000111 -
#289
0#
#290
1#
|(
b01100010 )
b10010001 *
b01111100 -
#291
0#
#292
1#
<'
u(
b01111001 )
b10010010 *
b10101111 +
b00011100 ,
b01110101 -
#293
0#
#294
1#
z(
b01110000 )
b10010011 *
b01111010 -
#295
0#
#296
1#
{(
b01101100 )
b10010100 *
b10110000 +
b01101011 -
#297
0#
#298
1#
s(
b10000110 )
b10010101 *
b10110001 +
b01100011 -
#299
0#
#300
1#
{(
b10000001 )
b10010110 *
b10110010 +
b01011011 -
#301
0#
#302
1#
y(
b01101101 )
b10010111 *
b10110011 +
b01001001 -
#303
0#
#304
1#
{(
b01111100 )
b10011000 *
b10110100 +
b01001011 -
#305
0#
#306
1#
|(
b01101111 )
b10011001 *
b10110101 +
b01011100 -
#307
0#
#308
1#
~(
b01100011 )
b10011010 *
b10110110 +
b01001110 -
#309
0#
#310
1#
v(
b01101101 )
b10011011 *
b10110111 +
b01000110 -
#311
0#
#312
1#
y(
b01101001 )
b10011100 *
b10111000 +
b01001001 -
#313
0#
#314
1#
u(
b01011010 )
b10011101 *
b10111001 +
b01000101 -
#315
0#
#316
1#
x(
b01001101 )
b10011110 *
b10111010 +
b01001000 -
#317
0#
#318
1#
w(
b01010001 )
b10011111 *
b10111011 +
b01000111 -
#319
0#
#320
1#
u(
b01011101 )
b10100000 *
b10111100 +
b01000101 -
#321
0#
#322
1#
;'
b01100011 )
b10100001 *
b10111101 +
b00011011 ,
#323
0#
#324
1#
:'
=(
b01011111 )
b10100010 *
b00011010 ,
b00111101 -
#325
0#
#326
1#
7'
?(
b01101000 )
b10100011 *
b00010111 ,
b00111111 -
#327
0#
#328
1#
6'
}(
b01110001 )
b10100100 *
b10111011 +
b00010110 ,
b01001101 -
#329
0#
#330
1#
5'
v(
b01010001 )
b10100101 *
b00010101 ,
b01010110 -
#331
0#
#332
1#
p(
b01001110 )
b10100110 *
b01010000 -
#333
0#
#334
1#
4'
v(
b01010010 )
b10100111 *
b10111100 +
b00010100 ,
b01010110 -
#335
0#
#336
1#
v(
b01011111 )
b10101000 *
b01100110 -
#337
0#
#338
1#
u(
b01100101 )
b10101001 *
b10111101 +
b01100101 -
#339
0#
#340
1#
b01101000 )
b10101010 *
b10111110 +
#341
0#
#342
1#
x(
b01111111 )
b10101011 *
b10111111 +
b01111000 -
#343
0#
#344
1#
~(
b01100010 )
b10101100 *
b11000000 +
b01111110 -
#345
0#
#346
1#
x(
b01010101 )
b10101101 *
b11000001 +
b01111000 -
#347
0#
#348
1#
3'
b01001001 )
b10101110 *
b11000010 +
b00010011 ,
#349
0#
#350
1#
?'
±(
b01111100 )
b10101111 *
b00001111 ,
b10000001 -
#351
0#
#352
1#
;'
´(
b01111010 )
b10110000 *
b10111111 +
b00001011 ,
b10000100 -
#353
0#
#354
1#
|(
b01101011 )
b10110001 *
b10111100 +
b01111100 -
#355
0#
#356
1#
²(
b01100011 )
b10110010 *
b10111101 +
b10000010 -
#357
0#
#358
1#
·(
b01011011 )
b10110011 *
b10111110 +
b10000111 -
#359
0#
#360
1#
{(
b01001001 )
b10110100 *
b10111111 +
b01111011 -
#361
0#
#362
1#
u(
b01001011 )
b10110101 *
b11000000 +
b01110101 -
#363
0#
#364
1#
z(
b01011100 )
b10110110 *
b11000001 +
b01111010 -
#365
0#
#366
1#
±(
b01001110 )
b10110111 *
b11000010 +
b10000001 -
#367
0#
#368
1#
¸(
b01000110 )
b10111000 *
b11000011 +
b10001000 -
#369
0#
#370
1#
|(
b01001001 )
b10111001 *
b11000100 +
b01111100 -
#371
0#
#372
1#
6'
·(
b01000101 )
b10111010 *
b11000101 +
b00000110 ,
b10000111 -
#373
0#
#374
1#
5'
»(
b01001000 )
b10111011 *
b11000001 +
b00000101 ,
b10001011 -
#375
0#
#376
1#
4'
~(
b01010000 )
b10111100 *
b00000100 ,
b01111110 -
#377
0#
#378
1#
°(
b01111100 )
b10111101 *
b10000000 -
#379
0#
#380
1#
}(
b10000010 )
b10111110 *
b11000010 +
b01111101 -
#381
0#
#382
1#
r(
b10000111 )
b10111111 *
b11000011 +
b01110010 -
#383
0#
#384
1#
(
b01111011 )
b11000000 *
b11000100 +
b01011111 -
#385
0#
#386
1#
|(
b01110101 )
b11000001 *
b11000101 +
b01001100 -
#387
0#
#388
1#
p(
b10000000 )
b11000010 *
b11000110 +
b01010000 -
#389
0#
#390
1#
~(
b01111101 )
b11000011 *
b11000111 +
b01001110 -
#391
0#
#392
1#
q(
b01110010 )
b11000100 *
b11001000 +
b01000001 -
#393
0#
#394
1#
3'
r(
b01011111 )
b11000101 *
b11001001 +
b00000011 ,
b01000010 -
#395
0#
#396
1#
2'
}(
b01001100 )
b11000110 *
b00000010 ,
b01001101 -
#397
0#
#398
1#
~(
b01010000 )
b11000111 *
b01001110 -
#399
0#
#400
1#
p(
b01001110 )
b11001000 *
b11001010 +
b01010000 -
#401
0#
#402
1#
y(
b01000001 )
b11001001 *
b11001011 +
b01101001 -
#403
0#
#404
1#
r(
b01001110 )
b11001010 *
b11001100 +
b01110010 -
#405
0#
#406
1#
u(
b01010000 )
b11001011 *
b11001101 +
b01110101 -
#407
0#
#408
1#
~(
b01101001 )
b11001100 *
b11001110 +
b01111110 -
#409
0#
#410
1#
v(
b01110010 )
b11001101 *
b11001111 +
b01110110 -
#411
0#
#412
1#
1'
s(
b01110101 )
b11001110 *
b11010000 +
b00000001 ,
b01110011 -
#413
0#
#414
1#
{(
b01111110 )
b11001111 *
b01111011 -
#415
0#
#416
1#
(
b01110110 )
b11010000 *
b11010001 +
b01101111 -
#417
0#
#418
1#
|(
b01111011 )
b11010001 *
b11010010 +
b01101100 -
#419
0#
#420
1#
p(
b01101111 )
b11010010 *
b11010011 +
b01110000 -
#421
0#
#422
1#
w(
b01101100 )
b11010011 *
b11010100 +
b01100111 -
#423
0#
#424
1#
|(
b01110000 )
b11010100 *
b11010101 +
b01011100 -
#425
0#
#426
1#
q(
b01100111 )
b11010101 *
b11010110 +
b01010001 -
#427
0#
#428
1#
w(
b01011100 )
b11010110 *
b11010111 +
b01010111 -
#429
0#
#430
1#
r(
b01010001 )
b11010111 *
b11011000 +
b01100010 -
#431
0#
#432
1#
x(
b01010111 )
b11011000 *
b11011001 +
b01101000 -
#433
0#
#434
1#
t(
b01100010 )
b11011001 *
b11011010 +
b01100100 -
#435
0#
#436
1#
0'
y(
b01101000 )
b11011010 *
b11011011 +
b00000000 ,
b01101001 -
#437
0#
#438
1#
{(
b01100100 )
b11011011 *
b01111011 -
#439
0#
#440
1#
y(
b01101001 )
b11011100 *
b11011100 +
b01111001 -
#441
0#
#442
1#
z(
b00000000 )
b11011101 *
b11011101 +
b01111010 -
#443
0#
#444
1#
¶(
b11011110 *
b11011110 +
b10000110 -
#445
0#
#446
1#
³(
b11011111 *
b11011111 +
b10000011 -
#447
0#
#448
1#
¸(
b11100000 *
b11100000 +
b10001000 -
#449
0#
#450
1#
¶(
b11100001 *
b11100001 +
b10000110 -
#451
0#
#452
1#
r(
b11100010 *
b11100010 +
b01110010 -
#453
0#
#454
1#
u(
b11100011 *
b11100011 +
b01110101 -
#455
0#
#456
1#
~(
b11100100 *
b11100100 +
b01111110 -
#457
0#
#458
1#
s(
b11100101 *
b11100101 +
b01110011 -
#459
0#
#460
1#
v(
b11100110 *
b11100110 +
b01110110 -
#461
0#
#462
1#
~(
b11100111 *
b11100111 +
b01101110 -
#463
0#
#464
1#
r(
b11101000 *
b11101000 +
b01110010 -
#465
0#
#466
1#
~(
b11101001 *
b11101001 +
b01111110 -
#467
0#
#468
1#
v(
b11101010 *
b11101010 +
b01110110 -
#469
0#
#470
1#
(
b11101011 *
b11101011 +
b01111111 -
#471
0#
#472
1#
{(
b11101100 *
b11101100 +
b01111011 -
#473
0#
#474
1#
x(
b11101101 *
b11101101 +
b01111000 -
#475
0#
#476
1#
u(
b11101110 *
b11101110 +
b01110101 -
#477
0#
#478
1#
¶(
b11101111 *
b11101111 +
b10000110 -
#479
0#
#480
1#
¸(
b11110000 *
b11110000 +
b10001000 -
#481
0#
#482
1#
y(
b11110001 *
b11110001 +
b01111001 -
#483
0#
#484
1#
³(
b11110010 *
b11110010 +
b10000011 -
#485
0#
#486
1#
±(
b11110011 *
b11110011 +
b10000001 -
#487
0#
#488
1#
z(
b11110100 *
b11110100 +
b01111010 -
#489
0#
#490
1#
w(
b11110101 *
b11110101 +
b01100111 -
#491
0#
#492
1#
p(
b11110110 *
b11110110 +
b01100000 -
#493
0#
#494
1#
}(
b11110111 *
b11110111 +
b01101101 -
#495
0#
#496
1#
b11111000 *
b11111000 +
#497
0#
#498
1#
y(
b11111001 *
b11111001 +
b01101001 -
#499
0#
#500
1#
q(
b11111010 *
b11111010 +
b01100001 -
#501
0#
#502
1#
z(
b11111011 *
b11111011 +
b01011010 -
#503
0#
#504
1#
|(
b11111100 *
b11111100 +
b01011100 -
#505
0#
#506
1#
}(
b11111101 *
b11111101 +
b01011101 -
#507
0#
#508
1#
u(
b11111110 *
b11111110 +
b01010101 -
#509
0#
#510
1#
y(
b11111111 *
b11111111 +
b01011001 -
#511
0#
#512
1#
z(
b00000000 *
b00000000 +
b01011010 -
#513
0#
#514
1#
x(
b00000001 *
b00000001 +
b01011000 -
#515
0#
#516
1#
p(
b00000010 *
b00000010 +
b01100000 -
#517
0#
#518
1#
v(
b00000011 *
b00000011 +
b01100110 -
#519
0#
#520
1#
z(
b00000100 *
b00000100 +
b01011010 -
#521
0#
#522
1#
r(
b00000101 *
b00000101 +
b01100010 -
#523
0#
#524
1#
x(
b00000110 *
b00000110 +
b01101000 -
#525
0#
#526
1#
q(
b00000111 *
b00000111 +
b01100001 -
#527
0#
#528
1#
w(
b00001000 *
b00001000 +
b01010111 -
#529
0#
#530
1#
w(
b00001001 *
b00001001 +
b01100111 -
#531
0#
#532
1#
t(
b00001010 *
b00001010 +
b01100100 -
#533
0#
#534
1#
y(
b00001011 *
b00001011 +
b01011001 -
#535
0#
#536
1#
~(
b00001100 *
b00001100 +
b01011110 -
#537
0#
#538
1#
{(
b00001101 *
b00001101 +
b01011011 -
#539
0#
#540
1#
w(
b00001110 *
b00001110 +
b01100111 -
#541
0#
#542
1#
~(
b00001111 *
b00001111 +
b01101110 -
#543
0#
#544
1#
u(
b00010000 *
b00010000 +
b01100101 -
#545
0#
#546
1#
r(
b00010001 *
b00010001 +
b01110010 -
#547
0#
#548
1#
´(
b00010010 *
b00010010 +
b10000100 -
#549
0#
#550
1#
¹(
b00010011 *
b00010011 +
b10001001 -
#551
0#
#552
1#
³(
b00010100 *
b00010100 +
b10000011 -
#553
0#
#554
1#
(
b00010101 *
b00010101 +
b01111111 -
#555
0#
#556
1#
b00010110 *
b00010110 +
#557
0#
#558
1#
´(
b00010111 *
b00010111 +
b10000100 -
#559
0#
#560
1#
s(
b00011000 *
b00011000 +
b01110011 -
#561
0#
#562
1#
r(
b00011001 *
b00011001 +
b01100010 -
#563
0#
#564
1#
b00011010 *
b00011010 +
#565
0#
#566
1#
~(
b00011011 *
b00011011 +
b01011110 -
#567
0#
#568
1#
r(
b00011100 *
b00011100 +
b01010010 -
#569
0#
#570
1#
z(
b00011101 *
b00011101 +
b01011010 -
#571
0#
#572
1#
(
b00011110 *
b00011110 +
b01011111 -
#573
0#
#574
1#
u(
b00011111 *
b00011111 +
b01010101 -
#575
0#
#576
1#
z(
b00100000 *
b00100000 +
b01011010 -
#577
0#
#578
1#
~(
b00100001 *
b00100001 +
b01011110 -
#579
0#
#580
1#
v(
b00100010 *
b00100010 +
b01100110 -
#581
0#
#582
1#
x(
b00100011 *
b00100011 +
b01111000 -
#583
0#
#584
1#
q(
b00100100 *
b00100100 +
b01110001 -
#585
0#
#586
1#
v(
b00100101 *
b00100101 +
b01110110 -
#587
0#
#588
1#
(
b00100110 *
b00100110 +
b01111111 -
#589
0#
#590
1#
y(
b00100111 *
b00100111 +
b01111001 -
#591
0#
#592
1#
v(
b00101000 *
b00101000 +
b01110110 -
#593
0#
#594
1#
(
b00101001 *
b00101001 +
b01111111 -
#595
0#
#596
1#
s(
b00101010 *
b00101010 +
b01110011 -
#597
0#
#598
1#
|(
b00101011 *
b00101011 +
b01101100 -
#599
0#
#600
1#
}(
b00101100 *
b00101100 +
b01111101 -
#601
0#
#602
1#
|(
b00101101 *
b00101101 +
b01101100 -
#603
0#
#604
1#
q(
b00101110 *
b00101110 +
b01100001 -
#605
0#
#606
1#
v(
b00101111 *
b00101111 +
b01100110 -
#607
0#
#608
1#
r(
b00110000 *
b00110000 +
b01100010 -
#609
0#
#610
1#
t(
b00110001 *
b00110001 +
b01100100 -
#611
0#
#612
1#
|(
b00110010 *
b00110010 +
b01101100 -
#613
0#
#614
1#
b00110011 *
b00110011 +
#615
0#
#616
1#
t(
b00110100 *
b00110100 +
b01100100 -
#617
0#
#618
1#
}(
b00110101 *
b00110101 +
b01101101 -
#619
0#
#620
1#
s(
b10001011 )
b00110110 *
b00110110 +
b01110011 -
#621
0#
#622
1#
p(
b10001001 )
b00110111 *
b00110111 +
b01110000 -
#623
0#
#624
1#
v(
b10010001 )
b00111000 *
b00111000 +
b01110110 -
#625
0#
#626
1#
s(
b10001101 )
b00111001 *
b00111001 +
b01110011 -
#627
0#
#628
1#
t(
b10011001 )
b00111010 *
b00111010 +
b01100100 -
#629
0#
#630
1#
y(
b10001110 )
b00111011 *
b00111011 +
b01101001 -
#631
0#
#632
1#
~(
b01110010 )
b00111100 *
b00111100 +
b01101110 -
#633
0#
#634
1#
t(
b01110100 )
b00111101 *
b00111101 +
b01100100 -
#635
0#
#636
1#
u(
b01110001 )
b00111110 *
b00111110 +
b01110101 -
#637
0#
#638
1#
s(
b01010111 )
b00111111 *
b00111111 +
b01110011 -
#639
0#
#640
1#
v(
b01011001 )
b01000000 *
b01000000 +
b01100110 -
#641
0#
#642
1#
|(
b01100010 )
b01000001 *
b01000001 +
b01011100 -
#643
0#
#644
1#
x(
b01010000 )
b01000010 *
b01000010 +
b01011000 -
#645
0#
#646
1#
}(
b01000011 *
b01000011 +
b01011101 -
#647
0#
#648
1#
~(
b01100110 )
b01000100 *
b01000100 +
b01011110 -
#649
0#
#650
1#
w(
b01010111 )
b01000101 *
b01000101 +
b01010111 -
#651
0#
#652
1#
(
b01011111 )
b01000110 *
b01000110 +
b01001111 -
#653
0#
#654
1#
~(
b01111000 )
b01000111 *
b01000111 +
b01101110 -
#655
0#
#656
1#
}(
b01110110 )
b01001000 *
b01001000 +
b01101101 -
#657
0#
#658
1#
z(
b01110010 )
b01001001 *
b01001001 +
b01101010 -
#659
0#
